cognee_community_tasks_codify/__init__.py
cognee_community_tasks_codify/enrich_dependency_graph_checker.py
cognee_community_tasks_codify/get_local_dependencies.py
cognee_community_tasks_codify/get_local_dependencies_checker.py
cognee_community_tasks_codify/get_non_code_files.py
cognee_community_tasks_codify/get_repo_dependency_graph_checker.py
cognee_community_tasks_codify/get_repo_file_dependencies.py
cognee_community_tasks_codify-0.1.0.dist-info/METADATA
cognee_community_tasks_codify-0.1.0.dist-info/WHEEL
cognee_community_tasks_codify-0.1.0.dist-info/RECORD
