Metadata-Version: 2.4
Name: cognee-community-tasks-codify
Version: 0.1.0
Summary: Package containing custom cognee tasks for the codify pipeline
Requires-Python: >=3.11,<=3.13
Classifier: Programming Language :: Python :: 3
Classifier: Programming Language :: Python :: 3.11
Classifier: Programming Language :: Python :: 3.12
Classifier: Programming Language :: Python :: 3.13
Requires-Dist: cognee (==0.5.0)
